eng_hindi/__init__.py
English_to_Hindi-0.0.1.dist-info/LICENSE
English_to_Hindi-0.0.1.dist-info/METADATA
English_to_Hindi-0.0.1.dist-info/WHEEL
English_to_Hindi-0.0.1.dist-info/top_level.txt
English_to_Hindi-0.0.1.dist-info/RECORD
