Metadata-Version: 2.1
Name: English to Hindi
Version: 0.0.1
Summary: This module helps in converting English sentences to Hindi
Home-page: UNKNOWN
Author: Anuj kumar
Author-email: kumaranuj01596@gmail.com
License: MIT
Platform: UNKNOWN
